{"chunk_definitions":[{"chunk_id":"cuqxv0aband9y","chunk_label":"load","document_id":"5056F213","expansion_state":0,"options":{"engine":"R","label":"load"},"row":13,"row_count":1,"visible":true},{"chunk_id":"cnfaiwxb6rrsk","chunk_label":"read data","document_id":"5056F213","expansion_state":0,"options":{"echo":false,"engine":"R","label":"read data","message":false},"row":19,"row_count":1,"visible":true},{"chunk_id":"cc1trvm6sa0r8","chunk_label":"plot","document_id":"5056F213","expansion_state":0,"options":{"engine":"R","label":"plot"},"row":24,"row_count":1,"visible":true}],"doc_write_time":1503520632}